[{"move_id":52,"move_name":"ultrices","move_accuracy":82,"move_power":9},
{"move_id":97,"move_name":"quam","move_accuracy":22,"move_power":43},
{"move_id":140,"move_name":"lacus","move_accuracy":65,"move_power":15},
{"move_id":19,"move_name":"nisi","move_accuracy":27,"move_power":36},
{"move_id":43,"move_name":"at","move_accuracy":65,"move_power":99},
{"move_id":167,"move_name":"nisi","move_accuracy":59,"move_power":83},
{"move_id":31,"move_name":"accumsan","move_accuracy":34,"move_power":34},
{"move_id":18,"move_name":"platea","move_accuracy":7,"move_power":83},
{"move_id":132,"move_name":"duis","move_accuracy":9,"move_power":72},
{"move_id":192,"move_name":"pretium","move_accuracy":14,"move_power":57}]
